nonebot_plugin_jm/Config.py
nonebot_plugin_jm/__init__.py
nonebot_plugin_jm/utils.py
nonebot_plugin_jm-0.4.1.dist-info/licenses/LICENSE
nonebot_plugin_jm-0.4.1.dist-info/METADATA
nonebot_plugin_jm-0.4.1.dist-info/WHEEL
nonebot_plugin_jm-0.4.1.dist-info/top_level.txt
nonebot_plugin_jm-0.4.1.dist-info/RECORD
