Metadata-Version: 2.4
Name: nonebot-plugin-jm
Version: 0.4.1
Summary: 下载 jm 漫画
License:                                  Apache License
Project-URL: Homepage, https://github.com/StillMisty/nonebot_plugin_jm
Requires-Python: >=3.10
License-File: LICENSE
Requires-Dist: nonebot-adapter-onebot>=2.3
Requires-Dist: nonebot2>=2.3
Requires-Dist: nonebot_plugin_alconna>=0.53
Requires-Dist: nonebot_plugin_localstore>=0.7
Requires-Dist: jmcomic>=2.5.0
Requires-Dist: pyzipper>=0.3.0
Dynamic: license-file
